kedro_telemetry/__init__.py
kedro_telemetry/masking.py
kedro_telemetry/plugin.py
kedro_telemetry-0.6.5.dist-info/METADATA
kedro_telemetry-0.6.5.dist-info/WHEEL
kedro_telemetry-0.6.5.dist-info/entry_points.txt
kedro_telemetry-0.6.5.dist-info/top_level.txt
kedro_telemetry-0.6.5.dist-info/RECORD
