Metadata-Version: 2.4
Name: kedro-telemetry
Version: 0.6.5
Summary: Kedro-Telemetry
Author: Kedro
License: Apache Software License (Apache 2.0)
Project-URL: Source, https://github.com/kedro-org/kedro-plugins/tree/main/kedro-telemetry
Project-URL: Documentation, https://github.com/kedro-org/kedro-plugins/blob/main/kedro-telemetry/README.md
Project-URL: Tracker, https://github.com/kedro-org/kedro-plugins/issues
Requires-Python: >=3.9
Requires-Dist: appdirs>=1.4.4
Requires-Dist: kedro<2.0.0,>=0.18.0
Requires-Dist: requests~=2.20
Requires-Dist: tomli>=1.1.0; python_version < "3.11"
Requires-Dist: tomli-w
Provides-Extra: test
Requires-Dist: pytest; extra == "test"
Requires-Dist: pytest-cov; extra == "test"
Requires-Dist: pytest-mock; extra == "test"
Requires-Dist: pytest-xdist[psutil]~=2.2.1; extra == "test"
Requires-Dist: PyYAML==5.3.1; extra == "test"
Requires-Dist: wheel; extra == "test"
Provides-Extra: lint
Requires-Dist: bandit<2.0,>=1.6.2; extra == "lint"
Requires-Dist: black~=22.0; extra == "lint"
Requires-Dist: detect-secrets~=1.5.0; extra == "lint"
Requires-Dist: mypy~=1.0; extra == "lint"
Requires-Dist: pre-commit>=2.9.2; extra == "lint"
Requires-Dist: ruff~=0.12.1; extra == "lint"
Requires-Dist: types-requests; extra == "lint"
Requires-Dist: types-PyYAML; extra == "lint"
